phenome_outlier_analysis/__init__.py
phenome_outlier_analysis/outlier_detector.py
phenome_outlier_analysis/phenome_outlier_analysis.py
tests/__init__.py
tests/test_outlier_detector.py
phenome_outlier_analysis-0.1.0.dist-info/METADATA
phenome_outlier_analysis-0.1.0.dist-info/WHEEL
phenome_outlier_analysis-0.1.0.dist-info/top_level.txt
phenome_outlier_analysis-0.1.0.dist-info/RECORD
